brynq_sdk_alight/__init__.py
brynq_sdk_alight/address.py
brynq_sdk_alight/employee.py
brynq_sdk_alight/job.py
brynq_sdk_alight/leave.py
brynq_sdk_alight/pay_elements.py
brynq_sdk_alight/salary.py
brynq_sdk_alight/termination.py
brynq_sdk_alight/time_elements.py
brynq_sdk_alight/time_quotas.py
brynq_sdk_alight/archive/flat_wrapper.py
brynq_sdk_alight/archive/hrxml_generator.py
brynq_sdk_alight/archive/managers.py
brynq_sdk_alight/archive/managers_generic.py
brynq_sdk_alight/archive/managers_old_complex.py
brynq_sdk_alight/archive/managers_simple.py
brynq_sdk_alight/schemas/__init__.py
brynq_sdk_alight/schemas/absence.py
brynq_sdk_alight/schemas/address.py
brynq_sdk_alight/schemas/employee.py
brynq_sdk_alight/schemas/job.py
brynq_sdk_alight/schemas/leave.py
brynq_sdk_alight/schemas/payments.py
brynq_sdk_alight/schemas/salary.py
brynq_sdk_alight/schemas/termination.py
brynq_sdk_alight/schemas/timequota.py
brynq_sdk_alight/schemas/utils.py
brynq_sdk_alight/schemas/generated_envelope_xsd_schema/__init__.py
brynq_sdk_alight/schemas/generated_envelope_xsd_schema/process_pay_serv_emp.py
brynq_sdk_alight/schemas/generated_xsd_schemas/__init__.py
brynq_sdk_alight/schemas/generated_xsd_schemas/csec_person.py
brynq_sdk_alight/schemas/generated_xsd_schemas/hrxml_indicative_data.py
brynq_sdk_alight/schemas/generated_xsd_schemas/openapplications_bod.py
brynq_sdk_alight/schemas/generated_xsd_schemas/openapplications_code_list_currency_code_iso_7_04.py
brynq_sdk_alight/schemas/generated_xsd_schemas/openapplications_code_list_language_code_iso_7_04.py
brynq_sdk_alight/schemas/generated_xsd_schemas/openapplications_code_list_mimemedia_type_code_iana_7_04.py
brynq_sdk_alight/schemas/generated_xsd_schemas/openapplications_code_list_unit_code_unece_7_04.py
brynq_sdk_alight/schemas/generated_xsd_schemas/openapplications_code_lists.py
brynq_sdk_alight/schemas/generated_xsd_schemas/openapplications_qualified_data_types.py
brynq_sdk_alight-1.0.0.dev0.dist-info/METADATA
brynq_sdk_alight-1.0.0.dev0.dist-info/WHEEL
brynq_sdk_alight-1.0.0.dev0.dist-info/top_level.txt
brynq_sdk_alight-1.0.0.dev0.dist-info/RECORD
