Metadata-Version: 2.4
Name: brynq_sdk_alight
Version: 1.0.0.dev0
Summary: Alight SDK for the BrynQ.com platform
Author: BrynQ
Author-email: support@brynq.com
License: BrynQ License
Requires-Dist: requests<=3,>=2
Requires-Dist: xsdata>=25.0.0
Requires-Dist: pydantic>=2.0.0
Requires-Dist: pydantic-xml>=2.0.0
Requires-Dist: xsdata-pydantic>=24.0.0
Dynamic: author
Dynamic: author-email
Dynamic: description
Dynamic: license
Dynamic: requires-dist
Dynamic: summary
